{
  "AUDCAD": {
    "bars_m15": 356100,
    "from": "2010-01-04",
    "to": "2026-04-30",
    "adx_mean": 24.3,
    "trend_efficiency_200": 0.068,
    "hurst": 0.471,
    "autocorr_lag1": -0.0603,
    "atr_pct_mean": 0.0798,
    "vol_of_vol": 0.402,
    "ou_half_life_m15": 12090.7,
    "kurtosis": 5.16,
    "pct_above_sma200": 0.511,
    "sma200_persistence_bars": 24.4,
    "vwap_rejection_rate": 0.894,
    "round_bounce_rate": 0.499,
    "rsi_long_edge_pct": 0.0112,
    "rsi_short_edge_pct": 0.0129,
    "rsi_combined_edge": 0.012,
    "rsi_edge_in_atrs": 0.151,
    "rsi_n_oversold": 13355,
    "rsi_n_overbought": 13657,
    "type": "forex",
    "subtype": "Minor",
    "editorial_ratings": {
      "momentum": "+",
      "regimen": "+",
      "estadistico": "+"
    }
  },
  "AUDJPY": {
    "bars_m15": 380027,
    "from": "2010-01-04",
    "to": "2026-04-30",
    "adx_mean": 24.84,
    "trend_efficiency_200": 0.075,
    "hurst": 0.489,
    "autocorr_lag1": -0.0246,
    "atr_pct_mean": 0.1085,
    "vol_of_vol": 0.502,
    "ou_half_life_m15": 21751.3,
    "kurtosis": 6.56,
    "pct_above_sma200": 0.538,
    "sma200_persistence_bars": 27.6,
    "vwap_rejection_rate": 0.89,
    "round_bounce_rate": 0.49,
    "rsi_long_edge_pct": 0.0046,
    "rsi_short_edge_pct": 0.0043,
    "rsi_combined_edge": 0.0045,
    "rsi_edge_in_atrs": 0.041,
    "rsi_n_oversold": 16345,
    "rsi_n_overbought": 17487,
    "type": "forex",
    "subtype": "Minor",
    "editorial_ratings": {
      "momentum": "+"
    }
  },
  "AUDNZD": {
    "bars_m15": 404905,
    "from": "2010-01-04",
    "to": "2026-04-30",
    "adx_mean": 24.26,
    "trend_efficiency_200": 0.0682,
    "hurst": 0.464,
    "autocorr_lag1": -0.091,
    "atr_pct_mean": 0.0673,
    "vol_of_vol": 0.474,
    "ou_half_life_m15": 32103.6,
    "kurtosis": 6.07,
    "pct_above_sma200": 0.497,
    "sma200_persistence_bars": 24.6,
    "vwap_rejection_rate": 0.894,
    "round_bounce_rate": 0.509,
    "rsi_long_edge_pct": 0.0121,
    "rsi_short_edge_pct": 0.0042,
    "rsi_combined_edge": 0.0082,
    "rsi_edge_in_atrs": 0.121,
    "rsi_n_oversold": 13739,
    "rsi_n_overbought": 13889,
    "type": "forex",
    "subtype": "Minor",
    "editorial_ratings": {
      "momentum": "+",
      "regimen": "++",
      "estadistico": "++"
    }
  },
  "AUDUSD": {
    "bars_m15": 405034,
    "from": "2010-01-04",
    "to": "2026-04-30",
    "adx_mean": 25.28,
    "trend_efficiency_200": 0.0761,
    "hurst": 0.49,
    "autocorr_lag1": -0.0228,
    "atr_pct_mean": 0.0932,
    "vol_of_vol": 0.522,
    "ou_half_life_m15": 65069.9,
    "kurtosis": 5.93,
    "pct_above_sma200": 0.506,
    "sma200_persistence_bars": 29.3,
    "vwap_rejection_rate": 0.888,
    "round_bounce_rate": 0.499,
    "rsi_long_edge_pct": -0.0012,
    "rsi_short_edge_pct": 0.0088,
    "rsi_combined_edge": 0.0038,
    "rsi_edge_in_atrs": 0.04,
    "rsi_n_oversold": 18307,
    "rsi_n_overbought": 18536,
    "type": "forex",
    "subtype": "Major",
    "editorial_ratings": {
      "momentum": "+",
      "regimen": "+"
    }
  },
  "CADCHF": {
    "bars_m15": 404958,
    "from": "2010-01-04",
    "to": "2026-04-30",
    "adx_mean": 24.16,
    "trend_efficiency_200": 0.0728,
    "hurst": 0.469,
    "autocorr_lag1": -0.0225,
    "atr_pct_mean": 0.0853,
    "vol_of_vol": 0.624,
    "ou_half_life_m15": 63498.2,
    "kurtosis": 7.17,
    "pct_above_sma200": 0.495,
    "sma200_persistence_bars": 26.3,
    "vwap_rejection_rate": 0.903,
    "round_bounce_rate": 0.499,
    "rsi_long_edge_pct": 0.0112,
    "rsi_short_edge_pct": 0.0084,
    "rsi_combined_edge": 0.0098,
    "rsi_edge_in_atrs": 0.114,
    "rsi_n_oversold": 16566,
    "rsi_n_overbought": 15436,
    "type": "forex",
    "subtype": "Minor",
    "editorial_ratings": {
      "regimen": "+",
      "estadistico": "+"
    }
  },
  "CADJPY": {
    "bars_m15": 405191,
    "from": "2010-01-04",
    "to": "2026-04-30",
    "adx_mean": 24.74,
    "trend_efficiency_200": 0.0769,
    "hurst": 0.49,
    "autocorr_lag1": -0.0196,
    "atr_pct_mean": 0.096,
    "vol_of_vol": 0.534,
    "ou_half_life_m15": 44126.8,
    "kurtosis": 6.7,
    "pct_above_sma200": 0.528,
    "sma200_persistence_bars": 27.9,
    "vwap_rejection_rate": 0.894,
    "round_bounce_rate": 0.493,
    "rsi_long_edge_pct": 0.007,
    "rsi_short_edge_pct": 0.0018,
    "rsi_combined_edge": 0.0044,
    "rsi_edge_in_atrs": 0.046,
    "rsi_n_oversold": 17353,
    "rsi_n_overbought": 19067,
    "type": "forex",
    "subtype": "Minor",
    "editorial_ratings": {
      "momentum": "+"
    }
  },
  "CHFJPY": {
    "bars_m15": 379942,
    "from": "2010-01-04",
    "to": "2026-04-30",
    "adx_mean": 24.3,
    "trend_efficiency_200": 0.0725,
    "hurst": 0.47,
    "autocorr_lag1": -0.0645,
    "atr_pct_mean": 0.0864,
    "vol_of_vol": 0.616,
    "ou_half_life_m15": 120000.0,
    "kurtosis": 6.51,
    "pct_above_sma200": 0.52,
    "sma200_persistence_bars": 26.5,
    "vwap_rejection_rate": 0.896,
    "round_bounce_rate": 0.513,
    "rsi_long_edge_pct": 0.01,
    "rsi_short_edge_pct": -0.0044,
    "rsi_combined_edge": 0.0028,
    "rsi_edge_in_atrs": 0.032,
    "rsi_n_oversold": 13860,
    "rsi_n_overbought": 15915,
    "type": "forex",
    "subtype": "Minor",
    "editorial_ratings": {
      "regimen": "+",
      "estadistico": "+"
    }
  },
  "EURAUD": {
    "bars_m15": 404967,
    "from": "2010-01-04",
    "to": "2026-04-30",
    "adx_mean": 25.14,
    "trend_efficiency_200": 0.0754,
    "hurst": 0.493,
    "autocorr_lag1": -0.036,
    "atr_pct_mean": 0.0828,
    "vol_of_vol": 0.511,
    "ou_half_life_m15": 31309.1,
    "kurtosis": 5.92,
    "pct_above_sma200": 0.48,
    "sma200_persistence_bars": 26.9,
    "vwap_rejection_rate": 0.891,
    "round_bounce_rate": 0.474,
    "rsi_long_edge_pct": 0.0103,
    "rsi_short_edge_pct": -0.0048,
    "rsi_combined_edge": 0.0027,
    "rsi_edge_in_atrs": 0.033,
    "rsi_n_oversold": 17883,
    "rsi_n_overbought": 18554,
    "type": "forex",
    "subtype": "Minor",
    "editorial_ratings": {
      "volatilidad": "+"
    }
  },
  "EURCAD": {
    "bars_m15": 404937,
    "from": "2010-01-04",
    "to": "2026-04-30",
    "adx_mean": 24.26,
    "trend_efficiency_200": 0.0759,
    "hurst": 0.489,
    "autocorr_lag1": -0.0359,
    "atr_pct_mean": 0.0723,
    "vol_of_vol": 0.544,
    "ou_half_life_m15": 17603.8,
    "kurtosis": 6.28,
    "pct_above_sma200": 0.501,
    "sma200_persistence_bars": 27.8,
    "vwap_rejection_rate": 0.904,
    "round_bounce_rate": 0.493,
    "rsi_long_edge_pct": 0.0069,
    "rsi_short_edge_pct": 0.0068,
    "rsi_combined_edge": 0.0068,
    "rsi_edge_in_atrs": 0.095,
    "rsi_n_oversold": 16671,
    "rsi_n_overbought": 17066,
    "type": "forex",
    "subtype": "Minor",
    "editorial_ratings": {
      "tendencia": "+",
      "sr": "+"
    }
  },
  "EURCHF": {
    "bars_m15": 403838,
    "from": "2010-01-04",
    "to": "2026-04-30",
    "adx_mean": 23.55,
    "trend_efficiency_200": 0.0659,
    "hurst": 0.483,
    "autocorr_lag1": -0.0385,
    "atr_pct_mean": 0.0524,
    "vol_of_vol": 0.749,
    "ou_half_life_m15": 37793.9,
    "kurtosis": 9.71,
    "pct_above_sma200": 0.473,
    "sma200_persistence_bars": 22.4,
    "vwap_rejection_rate": 0.907,
    "round_bounce_rate": 0.496,
    "rsi_long_edge_pct": 0.0099,
    "rsi_short_edge_pct": 0.0066,
    "rsi_combined_edge": 0.0082,
    "rsi_edge_in_atrs": 0.157,
    "rsi_n_oversold": 13298,
    "rsi_n_overbought": 13433,
    "type": "forex",
    "subtype": "Minor",
    "editorial_ratings": {
      "momentum": "+",
      "estadistico": "+"
    }
  },
  "EURGBP": {
    "bars_m15": 405015,
    "from": "2010-01-04",
    "to": "2026-04-30",
    "adx_mean": 24.47,
    "trend_efficiency_200": 0.0753,
    "hurst": 0.49,
    "autocorr_lag1": -0.0458,
    "atr_pct_mean": 0.065,
    "vol_of_vol": 0.598,
    "ou_half_life_m15": 15077.5,
    "kurtosis": 6.69,
    "pct_above_sma200": 0.487,
    "sma200_persistence_bars": 27.4,
    "vwap_rejection_rate": 0.902,
    "round_bounce_rate": 0.491,
    "rsi_long_edge_pct": 0.0021,
    "rsi_short_edge_pct": 0.0088,
    "rsi_combined_edge": 0.0055,
    "rsi_edge_in_atrs": 0.084,
    "rsi_n_oversold": 16601,
    "rsi_n_overbought": 16325,
    "type": "forex",
    "subtype": "Minor",
    "editorial_ratings": {
      "tendencia": "+",
      "regimen": "++",
      "sr": "+",
      "estadistico": "++"
    }
  },
  "EURJPY": {
    "bars_m15": 404973,
    "from": "2010-01-04",
    "to": "2026-04-30",
    "adx_mean": 24.96,
    "trend_efficiency_200": 0.078,
    "hurst": 0.495,
    "autocorr_lag1": -0.0165,
    "atr_pct_mean": 0.0861,
    "vol_of_vol": 0.54,
    "ou_half_life_m15": 120000.0,
    "kurtosis": 6.54,
    "pct_above_sma200": 0.524,
    "sma200_persistence_bars": 29.5,
    "vwap_rejection_rate": 0.887,
    "round_bounce_rate": 0.489,
    "rsi_long_edge_pct": 0.0044,
    "rsi_short_edge_pct": 0.002,
    "rsi_combined_edge": 0.0032,
    "rsi_edge_in_atrs": 0.037,
    "rsi_n_oversold": 17525,
    "rsi_n_overbought": 19295,
    "type": "forex",
    "subtype": "Minor",
    "editorial_ratings": {
      "tendencia": "+",
      "sr": "+"
    }
  },
  "EURNZD": {
    "bars_m15": 404806,
    "from": "2010-01-04",
    "to": "2026-04-30",
    "adx_mean": 24.63,
    "trend_efficiency_200": 0.0719,
    "hurst": 0.482,
    "autocorr_lag1": -0.0519,
    "atr_pct_mean": 0.0896,
    "vol_of_vol": 0.478,
    "ou_half_life_m15": 16311.7,
    "kurtosis": 5.22,
    "pct_above_sma200": 0.485,
    "sma200_persistence_bars": 26.5,
    "vwap_rejection_rate": 0.896,
    "round_bounce_rate": 0.48,
    "rsi_long_edge_pct": 0.013,
    "rsi_short_edge_pct": -0.0056,
    "rsi_combined_edge": 0.0037,
    "rsi_edge_in_atrs": 0.042,
    "rsi_n_oversold": 16083,
    "rsi_n_overbought": 16673,
    "type": "forex",
    "subtype": "Minor",
    "editorial_ratings": {
      "momentum": "+",
      "volatilidad": "+"
    }
  },
  "EURUSD": {
    "bars_m15": 380431,
    "from": "2010-01-04",
    "to": "2026-04-30",
    "adx_mean": 25.23,
    "trend_efficiency_200": 0.0809,
    "hurst": 0.497,
    "autocorr_lag1": -0.0185,
    "atr_pct_mean": 0.0703,
    "vol_of_vol": 0.603,
    "ou_half_life_m15": 23366.5,
    "kurtosis": 6.7,
    "pct_above_sma200": 0.5,
    "sma200_persistence_bars": 29.1,
    "vwap_rejection_rate": 0.896,
    "round_bounce_rate": 0.49,
    "rsi_long_edge_pct": -0.0003,
    "rsi_short_edge_pct": 0.0033,
    "rsi_combined_edge": 0.0015,
    "rsi_edge_in_atrs": 0.021,
    "rsi_n_oversold": 17104,
    "rsi_n_overbought": 17094,
    "type": "forex",
    "subtype": "Major",
    "editorial_ratings": {
      "tendencia": "++",
      "momentum": "+",
      "regimen": "+",
      "volumen": "+",
      "sr": "++",
      "estadistico": "+"
    }
  },
  "GBPAUD": {
    "bars_m15": 380120,
    "from": "2010-01-04",
    "to": "2026-04-30",
    "adx_mean": 24.84,
    "trend_efficiency_200": 0.0725,
    "hurst": 0.483,
    "autocorr_lag1": -0.0563,
    "atr_pct_mean": 0.0895,
    "vol_of_vol": 0.511,
    "ou_half_life_m15": 27793.0,
    "kurtosis": 5.82,
    "pct_above_sma200": 0.497,
    "sma200_persistence_bars": 26.4,
    "vwap_rejection_rate": 0.897,
    "round_bounce_rate": 0.491,
    "rsi_long_edge_pct": 0.0047,
    "rsi_short_edge_pct": 0.0019,
    "rsi_combined_edge": 0.0033,
    "rsi_edge_in_atrs": 0.037,
    "rsi_n_oversold": 15534,
    "rsi_n_overbought": 15691,
    "type": "forex",
    "subtype": "Minor",
    "editorial_ratings": {
      "tendencia": "+",
      "volatilidad": "+"
    }
  },
  "GBPCAD": {
    "bars_m15": 379651,
    "from": "2010-01-04",
    "to": "2026-04-30",
    "adx_mean": 24.02,
    "trend_efficiency_200": 0.0733,
    "hurst": 0.482,
    "autocorr_lag1": -0.0515,
    "atr_pct_mean": 0.0767,
    "vol_of_vol": 0.569,
    "ou_half_life_m15": 17766.5,
    "kurtosis": 6.28,
    "pct_above_sma200": 0.513,
    "sma200_persistence_bars": 26.4,
    "vwap_rejection_rate": 0.908,
    "round_bounce_rate": 0.494,
    "rsi_long_edge_pct": 0.0132,
    "rsi_short_edge_pct": 0.0059,
    "rsi_combined_edge": 0.0095,
    "rsi_edge_in_atrs": 0.124,
    "rsi_n_oversold": 14906,
    "rsi_n_overbought": 15055,
    "type": "forex",
    "subtype": "Minor",
    "editorial_ratings": {
      "tendencia": "+",
      "volatilidad": "+"
    }
  },
  "GBPCHF": {
    "bars_m15": 404936,
    "from": "2010-01-04",
    "to": "2026-04-30",
    "adx_mean": 24.25,
    "trend_efficiency_200": 0.0735,
    "hurst": 0.475,
    "autocorr_lag1": -0.0738,
    "atr_pct_mean": 0.0797,
    "vol_of_vol": 0.678,
    "ou_half_life_m15": 37092.7,
    "kurtosis": 7.14,
    "pct_above_sma200": 0.503,
    "sma200_persistence_bars": 26.6,
    "vwap_rejection_rate": 0.9,
    "round_bounce_rate": 0.512,
    "rsi_long_edge_pct": 0.0075,
    "rsi_short_edge_pct": 0.0065,
    "rsi_combined_edge": 0.007,
    "rsi_edge_in_atrs": 0.088,
    "rsi_n_oversold": 15984,
    "rsi_n_overbought": 15216,
    "type": "forex",
    "subtype": "Minor",
    "editorial_ratings": {
      "tendencia": "+",
      "sr": "+"
    }
  },
  "GBPJPY": {
    "bars_m15": 380031,
    "from": "2010-01-04",
    "to": "2026-04-30",
    "adx_mean": 24.69,
    "trend_efficiency_200": 0.0779,
    "hurst": 0.499,
    "autocorr_lag1": -0.0242,
    "atr_pct_mean": 0.0941,
    "vol_of_vol": 0.547,
    "ou_half_life_m15": 103398.0,
    "kurtosis": 6.29,
    "pct_above_sma200": 0.528,
    "sma200_persistence_bars": 28.0,
    "vwap_rejection_rate": 0.892,
    "round_bounce_rate": 0.494,
    "rsi_long_edge_pct": 0.003,
    "rsi_short_edge_pct": -0.0035,
    "rsi_combined_edge": -0.0003,
    "rsi_edge_in_atrs": -0.003,
    "rsi_n_oversold": 16107,
    "rsi_n_overbought": 17873,
    "type": "forex",
    "subtype": "Minor",
    "editorial_ratings": {
      "tendencia": "+",
      "momentum": "+",
      "volatilidad": "++",
      "sr": "+"
    }
  },
  "GBPNZD": {
    "bars_m15": 360271,
    "from": "2009-12-31",
    "to": "2026-04-30",
    "adx_mean": 24.39,
    "trend_efficiency_200": 0.069,
    "hurst": 0.472,
    "autocorr_lag1": -0.0635,
    "atr_pct_mean": 0.0946,
    "vol_of_vol": 0.49,
    "ou_half_life_m15": 11133.4,
    "kurtosis": 5.13,
    "pct_above_sma200": 0.496,
    "sma200_persistence_bars": 25.2,
    "vwap_rejection_rate": 0.901,
    "round_bounce_rate": 0.48,
    "rsi_long_edge_pct": 0.0165,
    "rsi_short_edge_pct": 0.0044,
    "rsi_combined_edge": 0.0105,
    "rsi_edge_in_atrs": 0.111,
    "rsi_n_oversold": 13254,
    "rsi_n_overbought": 13590,
    "type": "forex",
    "subtype": "Minor",
    "editorial_ratings": {
      "volatilidad": "+"
    }
  },
  "GBPUSD": {
    "bars_m15": 405029,
    "from": "2010-01-04",
    "to": "2026-04-30",
    "adx_mean": 24.86,
    "trend_efficiency_200": 0.0795,
    "hurst": 0.496,
    "autocorr_lag1": -0.027,
    "atr_pct_mean": 0.0728,
    "vol_of_vol": 0.58,
    "ou_half_life_m15": 38018.2,
    "kurtosis": 6.6,
    "pct_above_sma200": 0.499,
    "sma200_persistence_bars": 30.1,
    "vwap_rejection_rate": 0.9,
    "round_bounce_rate": 0.482,
    "rsi_long_edge_pct": -0.0035,
    "rsi_short_edge_pct": 0.0063,
    "rsi_combined_edge": 0.0014,
    "rsi_edge_in_atrs": 0.019,
    "rsi_n_oversold": 18249,
    "rsi_n_overbought": 17729,
    "type": "forex",
    "subtype": "Major",
    "editorial_ratings": {
      "tendencia": "+",
      "momentum": "+",
      "volatilidad": "++",
      "volumen": "+",
      "sr": "+"
    }
  },
  "GER40": {
    "bars_m15": 237604,
    "from": "2013-09-30",
    "to": "2026-04-30",
    "adx_mean": 25.75,
    "trend_efficiency_200": 0.0848,
    "hurst": 0.488,
    "autocorr_lag1": -0.0064,
    "atr_pct_mean": 0.1484,
    "vol_of_vol": 0.723,
    "ou_half_life_m15": 79767.9,
    "kurtosis": 10.43,
    "pct_above_sma200": 0.559,
    "sma200_persistence_bars": 29.9,
    "vwap_rejection_rate": 0.898,
    "round_bounce_rate": 0.485,
    "rsi_long_edge_pct": 0.0248,
    "rsi_short_edge_pct": -0.0092,
    "rsi_combined_edge": 0.0078,
    "rsi_edge_in_atrs": 0.053,
    "rsi_n_oversold": 11226,
    "rsi_n_overbought": 14770,
    "type": "index",
    "subtype": "DAX",
    "editorial_ratings": {
      "tendencia": "+",
      "tendencia_S": "-",
      "momentum": "+",
      "momentum_S": "+",
      "volatilidad_S": "+",
      "regimen": "+",
      "regimen_S": "+",
      "volumen": "+",
      "sr": "+",
      "sr_S": "+",
      "estadistico": "+"
    }
  },
  "NZDCAD": {
    "bars_m15": 351700,
    "from": "2010-01-04",
    "to": "2026-04-30",
    "adx_mean": 24.49,
    "trend_efficiency_200": 0.0684,
    "hurst": 0.467,
    "autocorr_lag1": -0.0739,
    "atr_pct_mean": 0.0906,
    "vol_of_vol": 0.414,
    "ou_half_life_m15": 15101.7,
    "kurtosis": 4.96,
    "pct_above_sma200": 0.507,
    "sma200_persistence_bars": 25.2,
    "vwap_rejection_rate": 0.896,
    "round_bounce_rate": 0.506,
    "rsi_long_edge_pct": 0.0135,
    "rsi_short_edge_pct": 0.0141,
    "rsi_combined_edge": 0.0138,
    "rsi_edge_in_atrs": 0.152,
    "rsi_n_oversold": 13412,
    "rsi_n_overbought": 12825,
    "type": "forex",
    "subtype": "Minor",
    "editorial_ratings": {
      "regimen": "+",
      "estadistico": "+"
    }
  },
  "NZDJPY": {
    "bars_m15": 354732,
    "from": "2010-01-04",
    "to": "2026-04-30",
    "adx_mean": 24.57,
    "trend_efficiency_200": 0.0731,
    "hurst": 0.481,
    "autocorr_lag1": -0.0386,
    "atr_pct_mean": 0.1168,
    "vol_of_vol": 0.475,
    "ou_half_life_m15": 29493.8,
    "kurtosis": 6.02,
    "pct_above_sma200": 0.532,
    "sma200_persistence_bars": 26.7,
    "vwap_rejection_rate": 0.892,
    "round_bounce_rate": 0.496,
    "rsi_long_edge_pct": 0.0043,
    "rsi_short_edge_pct": 0.0072,
    "rsi_combined_edge": 0.0057,
    "rsi_edge_in_atrs": 0.049,
    "rsi_n_oversold": 13883,
    "rsi_n_overbought": 15077,
    "type": "forex",
    "subtype": "Minor",
    "editorial_ratings": {
      "momentum": "+"
    }
  },
  "NZDUSD": {
    "bars_m15": 380183,
    "from": "2010-01-04",
    "to": "2026-04-30",
    "adx_mean": 25.03,
    "trend_efficiency_200": 0.0753,
    "hurst": 0.485,
    "autocorr_lag1": -0.0316,
    "atr_pct_mean": 0.1013,
    "vol_of_vol": 0.462,
    "ou_half_life_m15": 37023.2,
    "kurtosis": 5.27,
    "pct_above_sma200": 0.504,
    "sma200_persistence_bars": 28.2,
    "vwap_rejection_rate": 0.889,
    "round_bounce_rate": 0.485,
    "rsi_long_edge_pct": 0.0032,
    "rsi_short_edge_pct": 0.0084,
    "rsi_combined_edge": 0.0058,
    "rsi_edge_in_atrs": 0.057,
    "rsi_n_oversold": 16100,
    "rsi_n_overbought": 16694,
    "type": "forex",
    "subtype": "Major",
    "editorial_ratings": {
      "momentum": "+"
    }
  },
  "US30": {
    "bars_m15": 260881,
    "from": "2013-09-30",
    "to": "2026-04-30",
    "adx_mean": 25.88,
    "trend_efficiency_200": 0.0868,
    "hurst": 0.488,
    "autocorr_lag1": -0.0061,
    "atr_pct_mean": 0.1235,
    "vol_of_vol": 0.872,
    "ou_half_life_m15": 101851.0,
    "kurtosis": 13.14,
    "pct_above_sma200": 0.562,
    "sma200_persistence_bars": 30.6,
    "vwap_rejection_rate": 0.913,
    "round_bounce_rate": 0.505,
    "rsi_long_edge_pct": 0.0067,
    "rsi_short_edge_pct": -0.0076,
    "rsi_combined_edge": -0.0005,
    "rsi_edge_in_atrs": -0.004,
    "rsi_n_oversold": 12607,
    "rsi_n_overbought": 16677,
    "type": "index",
    "subtype": "Dow Jones",
    "editorial_ratings": {
      "tendencia": "++",
      "tendencia_S": "-",
      "momentum": "+",
      "momentum_S": "+",
      "volumen": "+",
      "volumen_S": "+",
      "sr": "+",
      "sr_S": "+"
    }
  },
  "US500": {
    "bars_m15": 279933,
    "from": "2011-09-18",
    "to": "2026-04-30",
    "adx_mean": 25.94,
    "trend_efficiency_200": 0.0859,
    "hurst": 0.489,
    "autocorr_lag1": -0.0062,
    "atr_pct_mean": 0.1273,
    "vol_of_vol": 0.949,
    "ou_half_life_m15": 104357.1,
    "kurtosis": 12.89,
    "pct_above_sma200": 0.585,
    "sma200_persistence_bars": 31.2,
    "vwap_rejection_rate": 0.913,
    "round_bounce_rate": 0.492,
    "rsi_long_edge_pct": 0.0145,
    "rsi_short_edge_pct": -0.0127,
    "rsi_combined_edge": 0.0009,
    "rsi_edge_in_atrs": 0.007,
    "rsi_n_oversold": 13200,
    "rsi_n_overbought": 19019,
    "type": "index",
    "subtype": "SP500",
    "editorial_ratings": {
      "tendencia": "++",
      "tendencia_S": "-",
      "momentum": "+",
      "momentum_S": "++",
      "volatilidad": "+",
      "volatilidad_S": "++",
      "regimen": "+",
      "regimen_S": "+",
      "volumen": "+",
      "volumen_S": "+",
      "sr": "+",
      "sr_S": "+",
      "estadistico": "+",
      "estadistico_S": "~"
    }
  },
  "USDCAD": {
    "bars_m15": 405014,
    "from": "2010-01-04",
    "to": "2026-04-30",
    "adx_mean": 24.38,
    "trend_efficiency_200": 0.0766,
    "hurst": 0.486,
    "autocorr_lag1": -0.0223,
    "atr_pct_mean": 0.0645,
    "vol_of_vol": 0.556,
    "ou_half_life_m15": 70539.3,
    "kurtosis": 6.28,
    "pct_above_sma200": 0.502,
    "sma200_persistence_bars": 26.7,
    "vwap_rejection_rate": 0.901,
    "round_bounce_rate": 0.482,
    "rsi_long_edge_pct": 0.0079,
    "rsi_short_edge_pct": 0.0031,
    "rsi_combined_edge": 0.0055,
    "rsi_edge_in_atrs": 0.085,
    "rsi_n_oversold": 17104,
    "rsi_n_overbought": 18068,
    "type": "forex",
    "subtype": "Major",
    "editorial_ratings": {
      "volatilidad": "+"
    }
  },
  "USDCHF": {
    "bars_m15": 404933,
    "from": "2010-01-04",
    "to": "2026-04-30",
    "adx_mean": 24.66,
    "trend_efficiency_200": 0.0779,
    "hurst": 0.475,
    "autocorr_lag1": -0.0303,
    "atr_pct_mean": 0.0737,
    "vol_of_vol": 0.626,
    "ou_half_life_m15": 16027.6,
    "kurtosis": 7.06,
    "pct_above_sma200": 0.51,
    "sma200_persistence_bars": 27.8,
    "vwap_rejection_rate": 0.899,
    "round_bounce_rate": 0.486,
    "rsi_long_edge_pct": 0.0008,
    "rsi_short_edge_pct": 0.0052,
    "rsi_combined_edge": 0.003,
    "rsi_edge_in_atrs": 0.041,
    "rsi_n_oversold": 17398,
    "rsi_n_overbought": 17212,
    "type": "forex",
    "subtype": "Major",
    "editorial_ratings": {
      "tendencia": "+",
      "sr": "+",
      "estadistico": "+"
    }
  },
  "USDJPY": {
    "bars_m15": 52917,
    "from": "2018-01-24",
    "to": "2026-04-30",
    "adx_mean": 24.98,
    "trend_efficiency_200": 0.0826,
    "hurst": 0.502,
    "autocorr_lag1": -0.017,
    "atr_pct_mean": 0.1124,
    "vol_of_vol": 0.88,
    "ou_half_life_m15": 1854.4,
    "kurtosis": 22.5,
    "pct_above_sma200": 0.552,
    "sma200_persistence_bars": 30.3,
    "vwap_rejection_rate": 0.934,
    "round_bounce_rate": 0.481,
    "rsi_long_edge_pct": -0.0232,
    "rsi_short_edge_pct": -0.0259,
    "rsi_combined_edge": -0.0245,
    "rsi_edge_in_atrs": -0.218,
    "rsi_n_oversold": 2595,
    "rsi_n_overbought": 3388,
    "type": "forex",
    "subtype": "Major",
    "editorial_ratings": {
      "tendencia": "+",
      "volatilidad": "+",
      "regimen": "+",
      "volumen": "+",
      "sr": "+"
    }
  },
  "USDMXN": {
    "bars_m15": 333793,
    "from": "2010-01-04",
    "to": "2026-04-30",
    "adx_mean": 25.03,
    "trend_efficiency_200": 0.077,
    "hurst": 0.49,
    "autocorr_lag1": -0.0227,
    "atr_pct_mean": 0.0972,
    "vol_of_vol": 0.827,
    "ou_half_life_m15": 56979.8,
    "kurtosis": 8.01,
    "pct_above_sma200": 0.464,
    "sma200_persistence_bars": 28.4,
    "vwap_rejection_rate": 0.906,
    "round_bounce_rate": 0.489,
    "rsi_long_edge_pct": 0.0151,
    "rsi_short_edge_pct": 0.007,
    "rsi_combined_edge": 0.011,
    "rsi_edge_in_atrs": 0.114,
    "rsi_n_oversold": 14790,
    "rsi_n_overbought": 15376,
    "type": "forex",
    "subtype": "Exotic",
    "editorial_ratings": {
      "volatilidad": "+"
    }
  },
  "USDZAR": {
    "bars_m15": 383129,
    "from": "2010-01-04",
    "to": "2026-04-30",
    "adx_mean": 24.98,
    "trend_efficiency_200": 0.0759,
    "hurst": 0.474,
    "autocorr_lag1": -0.0477,
    "atr_pct_mean": 0.1332,
    "vol_of_vol": 0.614,
    "ou_half_life_m15": 62834.6,
    "kurtosis": 4.88,
    "pct_above_sma200": 0.486,
    "sma200_persistence_bars": 27.8,
    "vwap_rejection_rate": 0.899,
    "round_bounce_rate": 0.501,
    "rsi_long_edge_pct": 0.0275,
    "rsi_short_edge_pct": 0.0044,
    "rsi_combined_edge": 0.0159,
    "rsi_edge_in_atrs": 0.12,
    "rsi_n_oversold": 16139,
    "rsi_n_overbought": 18299,
    "type": "forex",
    "subtype": "Exotic",
    "editorial_ratings": {
      "volatilidad": "+"
    }
  },
  "USTEC": {
    "bars_m15": 272924,
    "from": "2011-09-18",
    "to": "2026-04-30",
    "adx_mean": 26.43,
    "trend_efficiency_200": 0.0905,
    "hurst": 0.494,
    "autocorr_lag1": 0.0001,
    "atr_pct_mean": 0.1617,
    "vol_of_vol": 1.029,
    "ou_half_life_m15": 120000.0,
    "kurtosis": 11.28,
    "pct_above_sma200": 0.592,
    "sma200_persistence_bars": 32.8,
    "vwap_rejection_rate": 0.911,
    "round_bounce_rate": 0.5,
    "rsi_long_edge_pct": 0.006,
    "rsi_short_edge_pct": -0.0267,
    "rsi_combined_edge": -0.0104,
    "rsi_edge_in_atrs": -0.064,
    "rsi_n_oversold": 13779,
    "rsi_n_overbought": 20507,
    "type": "index",
    "subtype": "Nasdaq",
    "editorial_ratings": {
      "tendencia": "++",
      "tendencia_S": "-",
      "momentum": "++",
      "momentum_S": "++",
      "volatilidad": "+",
      "volatilidad_S": "++",
      "regimen": "+",
      "regimen_S": "+",
      "volumen": "+",
      "volumen_S": "+",
      "sr": "+",
      "sr_S": "+",
      "estadistico": "+",
      "estadistico_S": "~"
    }
  },
  "XAUUSD": {
    "bars_m15": 380084,
    "from": "2010-01-04",
    "to": "2026-04-30",
    "adx_mean": 25.62,
    "trend_efficiency_200": 0.0833,
    "hurst": 0.493,
    "autocorr_lag1": -0.0106,
    "atr_pct_mean": 0.1312,
    "vol_of_vol": 1.174,
    "ou_half_life_m15": 120000,
    "kurtosis": 9.72,
    "pct_above_sma200": 0.53,
    "sma200_persistence_bars": 29.6,
    "vwap_rejection_rate": 0.897,
    "round_bounce_rate": 0.492,
    "rsi_long_edge_pct": 0.0164,
    "rsi_short_edge_pct": -0.0136,
    "rsi_combined_edge": 0.0014,
    "rsi_edge_in_atrs": 0.011,
    "rsi_n_oversold": 16572,
    "rsi_n_overbought": 19710,
    "type": "oro",
    "subtype": "Oro",
    "editorial_ratings": {
      "tendencia": "++",
      "tendencia_S": "~",
      "momentum": "+",
      "momentum_S": "++",
      "volatilidad": "+",
      "volatilidad_S": "+",
      "regimen": "+",
      "regimen_S": "+",
      "volumen": "+",
      "sr": "++",
      "sr_S": "+",
      "estadistico": "+"
    }
  }
}